Workbook

Sheet README
A1: Capital Call Engine — Input Template & Specification
A2: Fill the YELLOW cells. Blue text = you enter it. Grey = the engine computes it. Pink = illustrative example only.
B4: What this workbook is
B5: One file that serves three audiences: (1) the CLIENT fills a handful of tabs in ~10-15 minutes; (2) your DEVELOPER reads it as the data contract for the calculation engine; (3) it ships with a live, self-computing 'Expected_Output' tab that acts as a golden test case to validate the engine's numbers.
B7: Tabs the client fills each call
B8: Fund_Setup — one-time / per-call fund parameters (currency, call no., dates, default fee, rounding rule).
B9: LP_Register — the investor roster. Entered once, then carried forward and only edited for changes.
B10: Call_Components — the line items being called THIS time (each deal + each expense), with its allocation basis.
B11: Management_Fee — fee rate, basis, period and any fee offsets. Per-LP side-letter rates live in LP_Register.
B12: Transfers — OPTIONAL. Only when an LP interest is transferred (full or partial) before the call.
B14: Tabs for the developer
B15: Data_Dictionary — every field, its type, whether required, allowed values and validation notes.
B16: Expected_Output — the fully worked example, computed live from the input tabs. Use it as a regression fixture.
B18: The calculation engine — order of operations
... B51: Template v1.0 — carry the fund name, call number and 'prepared by / date' at the top of Fund_Setup so every generated notice is traceable to the exact input file that produced it.

Sheet Fund_Setup
A1: Fund Setup
A2: One row per field. Enter values in the yellow column.
A3: Field | B3: Value | C3: Notes / allowed values
A4: Fund_Name | B4: Illustrative Fund II, L.P. | C4: Free text; shown on every notice.
A5: Reporting_Currency | B5: USD | C5: ISO code.
A6: Call_Number | B6: 2 | C6: Integer. Increment each call.
A7: Call_Date | B7: 46295 | C7: Effective date of the call.
A8: Payment_Due_Date | B8: 46309 | C8: When LP wires are due.
A9: Default_Mgmt_Fee_Rate_Annual | B9: 0.02 | C9: Fraction. 0.02 = 2%. Overridden per-LP in LP_Register.
A10: Default_Mgmt_Fee_Basis | B10: Commitment | C10: Commitment | Invested_Capital | NAV.
A11: Mgmt_Fee_Period_Fraction | B11: 0.25 | C11: Portion of the annual fee being called. 0.25 = one quarter.
A12: Org_Expense_Cap | B12: 1500000 | C12: Cap on organizational expenses; excess treated per LPA.
A13: Rounding_Decimals | B13: 2 | C13: Decimal places for every allocation.
A14: Rounding_Plug_LP_ID | B14: LP04 | C14: LP that absorbs the rounding residual (usually the largest).
A15: Prepared_By | B15: Ops Team | C15: Traceability.

Sheet LP_Register
A1: LP Register (investor roster)
A2: Enter once, then carry forward. Opening balances are AS AT the start of this call. Yellow = you enter.
A3: LP_ID | B3: LP_Name | C3: LP_Type | D3: Commitment | E3: Opening_Paid_In | F3: Opening_UCC | G3: Opening_Invested_Capital | H3: Mgmt_Fee_Rate_Override | I3: Fee_Exempt | J3: Status | K3: Side_Letter_Ref | L3: Notes
A4: LP01 | B4: Alpha Pension Trust | C4: LP | D4: 10000000 | E4: 2000000 | F4: 8000000 | G4: 1800000 | I4: N | J4: Active
A5: LP02 | B5: Beta University Endowment | C5: LP | D5: 7500000 | E5: 750000 | F5: 6750000 | G5: 675000 | I5: N | J5: Active
A6: LP03 | B6: Gamma Family Office | C6: LP | D6: 5000000 | E6: 2000000 | F6: 3000000 | G6: 1800000 | H6: 0.01 | I6: N | J6: Active | K6: SL-2024-03 | L6: Mgmt fee reduced to 1% per side letter
A7: LP04 | B7: Delta Insurance Co | C7: LP | D7: 15000000 | E7: 1500000 | F7: 13500000 | G7: 1350000 | I7: N | J7: Active | L7: Largest commitment; rounding plug
A8: LP05 | B8: Epsilon Sovereign Fund | C8: LP | D8: 12500000 | E8: 3500000 | F8: 9000000 | G8: 3150000 | I8: N | J8: Active
A9: GP01 | B9: Fund GP LLC | C9: GP | D9: 500000 | E9: 50000 | F9: 450000 | G9: 45000 | I9: Y | J9: Active | L9: GP commitment; exempt from mgmt fee

Sheet Call_Components
A1: Call Components (line items for THIS call)
A2: One row per deal and per expense. Management fee is configured on the Management_Fee tab (do not list it here).
A3: Component_ID | B3: Component_Name | C3: Category | D3: Total_Amount | E3: Allocation_Basis | F3: Reduces_Unfunded | G3: Excused_LP_IDs | H3: Notes
A4: C1 | B4: Deal X | C4: Deal | D4: 3000000 | E4: Commitment | F4: Y | H4: Allocated on committed capital.
A5: C2 | B5: Deal Y | C5: Deal | D5: 2000000 | E5: Commitment | F5: Y | H5: Allocated on committed capital.
A6: C3 | B6: Deal Z | C6: Deal | D6: 1500000 | E6: UCC | F6: Y | H6: Allocated on UNFUNDED commitment, not commitment.
A7: C4 | B7: Partnership Expense | C7: Partnership Expense | D7: 200000 | E7: Commitment | F7: Y | H7: Ongoing fund expense; inside commitment.
A8: C5 | B8: Organizational Expense | C8: Organizational Expense | D8: 150000 | E8: Commitment | F8: N | H8: OUTSIDE commitment: contributed but does NOT reduce unfunded.

Sheet Management_Fee
A1: Management Fee
A2: Default rate is here; per-LP side-letter rates live in LP_Register (Mgmt_Fee_Rate_Override).
A3: Field | B3: Value | C3: Notes
A4: Fee_Basis | B4: Commitment | C4: Commitment | Invested_Capital | NAV. Switch to Invested_Capital post-investment-period.
A5: Default_Fee_Rate_Annual | B5: 0.02 | C5: Fraction. 0.02 = 2%.
A6: Fee_Period_Fraction | B6: 0.25 | C6: Portion of annual fee called now. 0.25 = one quarter.
A7: Reduces_Unfunded | B7: Y | C7: Y if the fee is drawn from commitment.
A8: Fee_Exempt_LP_IDs | B8: GP01 | C8: Comma-separated LP_IDs charged 0% (e.g. the GP).
A10: Offsets
A11: Offset_ID | B11: Description | C11: Amount | D11: Allocation_Method
A12: O1 | B12: GP transaction fee offset (100% sharing) | C12: 50000 | D12: Pro-rata to gross fee

Sheet Transfers
A1: Transfers (OPTIONAL)
A2: One row per transfer, applied BEFORE the call is allocated. Partial = give Transfer_Pct. The row below is ILLUSTRATIVE (pink) and effective NEXT call — it is NOT applied to Call 2.
A3: Transfer_ID | B3: Effective_Date | C3: From_LP_ID | D3: To_LP_ID | E3: To_LP_Name_if_new | F3: Transfer_Type | G3: Transfer_Pct | H3: Transfers_Commitment | I3: Transfers_Paid_In | J3: Transfers_UCC | K3: Notes
A4: T1 | B4: 46387 | C4: LP05 | D4: LP06 | E4: Zeta Capital Partners | F4: Partial | G4: 0.4 | H4: Y | I4: Y | J4: Y | K4: ILLUSTRATIVE: 40% of LP05's position to new LP06, effective next call.

Sheet Expected_Output
A1: Expected Output — golden test case (computed live)
A2: Formulas pull from the input tabs. Deal X/Y/Partnership/Org on Commitment; Deal Z on UCC; fee per-LP rate with pro-rata offset. Rounding residual plugs to LP04. Use as a regression fixture for the engine.
A3: LP_ID | B3: LP_Name | C3: Commitment | D3: Opening_UCC | E3: Opening_Paid_In | F3: Deal_X | G3: Deal_Y | H3: Deal_Z | I3: Partnership_Exp | J3: Org_Exp | K3: Fee_Rate | L3: Fee_Gross | M3: Fee_Offset | N3: Fee_Net | O3: Total_Call | P3: Reduces_Unfunded_Amt | Q3: Closing_UCC | R3: Closing_Paid_In
A4: =LP_Register!A4 -> LP01 | B4: =LP_Register!B4 -> Alpha Pension Trust | C4: =LP_Register!D4 -> 10000000 | D4: =LP_Register!F4 -> 8000000 | E4: =LP_Register!E4 -> 2000000 | F4: =ROUND($B$14*C4/$B$22,2) -> 594059.41 | G4: =ROUND($B$15*C4/$B$22,2) -> 396039.6 | H4: =ROUND($B$16*D4/$B$23,2) -> 294840.29 | I4: =ROUND($B$17*C4/$B$22,2) -> 39603.96 | J4: =ROUND($B$18*C4/$B$22,2) -> 29702.97 | K4: =IF(ISNUMBER(SEARCH(A4,Management_Fee!$B$8)),0,IF(N(LP_Register!H4)>0,LP_Register!H4,$B$19)) -> 0.02 | L4: =ROUND(C4*K4*$B$20,2) -> 50000 | M4: =IFERROR(ROUND($B$21*L4/$B$24,2),0) -> 10526.32 | N4: =L4-M4 -> 39473.68 | O4: =F4+G4+H4+I4+J4+N4 -> 1393719.9 | P4: =F4+G4+H4+I4+N4 -> 1364016.9 | Q4: =D4-P4 -> 6635983.1 | R4: =E4+O4 -> 3393719.9
A5: =LP_Register!A5 -> LP02 | B5: =LP_Register!B5 -> Beta University Endowment | C5: =LP_Register!D5 -> 7500000 | D5: =LP_Register!F5 -> 6750000 | E5: =LP_Register!E5 -> 750000 | F5: =ROUND($B$14*C5/$B$22,2) -> 445544.55 | G5: =ROUND($B$15*C5/$B$22,2) -> 297029.7 | H5: =ROUND($B$16*D5/$B$23,2) -> 248771.5 | I5: =ROUND($B$17*C5/$B$22,2) -> 29702.97 | J5: =ROUND($B$18*C5/$B$22,2) -> 22277.23 | K5: =IF(ISNUMBER(SEARCH(A5,Management_Fee!$B$8)),0,IF(N(LP_Register!H5)>0,LP_Register!H5,$B$19)) -> 0.02 | L5: =ROUND(C5*K5*$B$20,2) -> 37500 | M5: =IFERROR(ROUND($B$21*L5/$B$24,2),0) -> 7894.74 | N5: =L5-M5 -> 29605.26 | O5: =F5+G5+H5+I5+J5+N5 -> 1072931.2 | P5: =F5+G5+H5+I5+N5 -> 1050654 | Q5: =D5-P5 -> 5699346 | R5: =E5+O5 -> 1822931.2
A6: =LP_Register!A6 -> LP03 | B6: =LP_Register!B6 -> Gamma Family Office | C6: =LP_Register!D6 -> 5000000 | D6: =LP_Register!F6 -> 3000000 | E6: =LP_Register!E6 -> 2000000 | F6: =ROUND($B$14*C6/$B$22,2) -> 297029.7 | G6: =ROUND($B$15*C6/$B$22,2) -> 198019.8 | H6: =ROUND($B$16*D6/$B$23,2) -> 110565.11 | I6: =ROUND($B$17*C6/$B$22,2) -> 19801.98 | J6: =ROUND($B$18*C6/$B$22,2) -> 14851.49 | K6: =IF(ISNUMBER(SEARCH(A6,Management_Fee!$B$8)),0,IF(N(LP_Register!H6)>0,LP_Register!H6,$B$19)) -> 0.01 | L6: =ROUND(C6*K6*$B$20,2) -> 12500 | M6: =IFERROR(ROUND($B$21*L6/$B$24,2),0) -> 2631.58 | N6: =L6-M6 -> 9868.42 | O6: =F6+G6+H6+I6+J6+N6 -> 650136.5 | P6: =F6+G6+H6+I6+N6 -> 635285.01 | Q6: =D6-P6 -> 2364715 | R6: =E6+O6 -> 2650136.5
A7: =LP_Register!A7 -> LP04 | B7: =LP_Register!B7 -> Delta Insurance Co | C7: =LP_Register!D7 -> 15000000 | D7: =LP_Register!F7 -> 13500000 | E7: =LP_Register!E7 -> 1500000 | F7: =ROUND($B$14-(SUM(F4:F6)+SUM(F8:F9)),2) -> 891089.11 | G7: =ROUND($B$15-(SUM(G4:G6)+SUM(G8:G9)),2) -> 594059.42 | H7: =ROUND($B$16-(SUM(H4:H6)+SUM(H8:H9)),2) -> 497543 | I7: =ROUND($B$17-(SUM(I4:I6)+SUM(I8:I9)),2) -> 59405.94 | J7: =ROUND($B$18-(SUM(J4:J6)+SUM(J8:J9)),2) -> 44554.45 | K7: =IF(ISNUMBER(SEARCH(A7,Management_Fee!$B$8)),0,IF(N(LP_Register!H7)>0,LP_Register!H7,$B$19)) -> 0.02 | L7: =ROUND(C7*K7*$B$20,2) -> 75000 | M7: =ROUND($B$21-(SUM(M4:M6)+SUM(M8:M9)),2) -> 15789.47 | N7: =L7-M7 -> 59210.53 | O7: =F7+G7+H7+I7+J7+N7 -> 2145862.5 | P7: =F7+G7+H7+I7+N7 -> 2101308 | Q7: =D7-P7 -> 11398692 | R7: =E7+O7 -> 3645862.5
A8: =LP_Register!A8 -> LP05 | B8: =LP_Register!B8 -> Epsilon Sovereign Fund | C8: =LP_Register!D8 -> 12500000 | D8: =LP_Register!F8 -> 9000000 | E8: =LP_Register!E8 -> 3500000 | F8: =ROUND($B$14*C8/$B$22,2) -> 742574.26 | G8: =ROUND($B$15*C8/$B$22,2) -> 495049.5 | H8: =ROUND($B$16*D8/$B$23,2) -> 331695.33 | I8: =ROUND($B$17*C8/$B$22,2) -> 49504.95 | J8: =ROUND($B$18*C8/$B$22,2) -> 37128.71 | K8: =IF(ISNUMBER(SEARCH(A8,Management_Fee!$B$8)),0,IF(N(LP_Register!H8)>0,LP_Register!H8,$B$19)) -> 0.02 | L8: =ROUND(C8*K8*$B$20,2) -> 62500 | M8: =IFERROR(ROUND($B$21*L8/$B$24,2),0) -> 13157.89 | N8: =L8-M8 -> 49342.11 | O8: =F8+G8+H8+I8+J8+N8 -> 1705294.9 | P8: =F8+G8+H8+I8+N8 -> 1668166.1 | Q8: =D8-P8 -> 7331833.8 | R8: =E8+O8 -> 5205294.9
A9: =LP_Register!A9 -> GP01 | B9: =LP_Register!B9 -> Fund GP LLC | C9: =LP_Register!D9 -> 500000 | D9: =LP_Register!F9 -> 450000 | E9: =LP_Register!E9 -> 50000 | F9: =ROUND($B$14*C9/$B$22,2) -> 29702.97 | G9: =ROUND($B$15*C9/$B$22,2) -> 19801.98 | H9: =ROUND($B$16*D9/$B$23,2) -> 16584.77 | I9: =ROUND($B$17*C9/$B$22,2) -> 1980.2 | J9: =ROUND($B$18*C9/$B$22,2) -> 1485.15 | K9: =IF(ISNUMBER(SEARCH(A9,Management_Fee!$B$8)),0,IF(N(LP_Register!H9)>0,LP_Register!H9,$B$19)) -> 0 | L9: =ROUND(C9*K9*$B$20,2) -> 0 | M9: =IFERROR(ROUND($B$21*L9/$B$24,2),0) -> 0 | N9: =L9-M9 -> 0 | O9: =F9+G9+H9+I9+J9+N9 -> 69555.07 | P9: =F9+G9+H9+I9+N9 -> 68069.92 | Q9: =D9-P9 -> 381930.08 | R9: =E9+O9 -> 119555.07
B10: TOTAL | C10: =SUM(C4:C9) -> 50500000 | D10: =SUM(D4:D9) -> 40700000 | E10: =SUM(E4:E9) -> 9800000 | F10: =SUM(F4:F9) -> 3000000 | G10: =SUM(G4:G9) -> 2000000 | H10: =SUM(H4:H9) -> 1500000 | I10: =SUM(I4:I9) -> 200000 | J10: =SUM(J4:J9) -> 150000 | L10: =SUM(L4:L9) -> 237500 | M10: =SUM(M4:M9) -> 50000 | N10: =SUM(N4:N9) -> 187500 | O10: =SUM(O4:O9) -> 7037500 | P10: =SUM(P4:P9) -> 6887500 | Q10: =SUM(Q4:Q9) -> 33812500 | R10: =SUM(R4:R9) -> 16837500
A13: CALL PARAMETERS (linked from input tabs)
A14: Deal_X_Amount | B14: =Call_Components!D4 -> 3000000
A15: Deal_Y_Amount | B15: =Call_Components!D5 -> 2000000
A16: Deal_Z_Amount | B16: =Call_Components!D6 -> 1500000
A17: Partnership_Exp_Amount | B17: =Call_Components!D7 -> 200000
A18: Org_Exp_Amount | B18: =Call_Components!D8 -> 150000
A19: Mgmt_Fee_Default_Rate | B19: =Management_Fee!B5 -> 0.02
A20: Mgmt_Fee_Period | B20: =Management_Fee!B6 -> 0.25
A21: Mgmt_Fee_Offset_Amount | B21: =Management_Fee!C12 -> 50000
A22: Commitment_Total | B22: =SUM(C4:C9) -> 50500000
A23: UCC_Total | B23: =SUM(D4:D9) -> 40700000
A24: Gross_Fee_Total | B24: =SUM(L4:L9) -> 237500

Sheet Data_Dictionary
A1: Data Dictionary (for the developer)
A2: Field-level contract for each input tab.
A3: Tab | B3: Field | C3: Type | D3: Required | E3: Allowed / validation | F3: Description
A4: Fund_Setup | B4: Fund_Name | C4: text | D4: Y | F4: Display name on notices.
A5: Fund_Setup | B5: Call_Number | C5: int | D5: Y | E5: >=1 | F5: Sequential call identifier.
A6: Fund_Setup | B6: Call_Date / Payment_Due_Date | C6: date | D6: Y | F6: Call effective date and wire due date.
A7: Fund_Setup | B7: Default_Mgmt_Fee_Rate_Annual | C7: decimal | D7: Y | E7: 0-1 (fraction) | F7: Default annual fee rate.
A8: Fund_Setup | B8: Default_Mgmt_Fee_Basis | C8: enum | D8: Y | E8: Commitment|Invested_Capital|NAV | F8: Default fee basis.
A9: Fund_Setup | B9: Mgmt_Fee_Period_Fraction | C9: decimal | D9: Y | E9: 0-1 | F9: Portion of annual fee called.
A10: Fund_Setup | B10: Rounding_Decimals | C10: int | D10: Y | E10: >=0 | F10: Precision for allocations.
A11: Fund_Setup | B11: Rounding_Plug_LP_ID | C11: text(FK) | D11: Y | E11: valid LP_ID | F11: Absorbs rounding residual.
A12: LP_Register | B12: LP_ID | C12: text(PK) | D12: Y | E12: unique, stable | F12: Primary key; never reused, survives transfers.
A13: LP_Register | B13: LP_Name | C13: text | D13: Y | F13: Legal name for the notice.
A14: LP_Register | B14: LP_Type | C14: enum | D14: Y | E14: LP|GP|Feeder | F14: Investor class.
A15: LP_Register | B15: Commitment | C15: money | D15: Y | E15: >=0 | F15: Total committed capital.
A16: LP_Register | B16: Opening_Paid_In | C16: money | D16: Y | E16: >=0 | F16: Cumulative contributions before this call.
A17: LP_Register | B17: Opening_UCC | C17: money | D17: Y | E17: >=0 | F17: Unfunded commitment before this call.
A18: LP_Register | B18: Opening_Invested_Capital | C18: money | D18: N | E18: >=0 | F18: For Invested_Capital fee/allocation basis.
A19: LP_Register | B19: Mgmt_Fee_Rate_Override | C19: decimal | D19: N | E19: 0-1 | F19: Side-letter fee rate; blank = use default.
A20: LP_Register | B20: Fee_Exempt | C20: enum | D20: N | E20: Y|N | F20: Y = 0% fee regardless of override.
A21: LP_Register | B21: Status | C21: enum | D21: Y | E21: Active|Transferred|Defaulted|Withdrawn | F21: Lifecycle state.
A22: Call_Components | B22: Component_ID | C22: text(PK) | D22: Y | E22: unique | F22: Line-item key.
A23: Call_Components | B23: Category | C23: enum | D23: Y | E23: Deal|Partnership Expense|Organizational Expense|Other Expense | F23: Line-item type.
A24: Call_Components | B24: Total_Amount | C24: money | D24: Y | E24: >0 | F24: Amount to raise for this line.
A25: Call_Components | B25: Allocation_Basis | C25: enum | D25: Y | E25: Commitment|UCC|Invested_Capital | F25: How to split it.
... A37: Transfers | B37: Transfers_Commitment/Paid_In/UCC | C37: enum | D37: cond | E37: Y|N | F37: Which positions move with the interest.
